<annotation>
	<folder>VOC2010</folder>
	<originalfile>2068061555_064235da9a.jpg</originalfile>
	<filename>action0751.jpg</filename>
	<source>
		<database>MyDatabase</database>
		<annotation>MyAnnotation</annotation>
		<image>flickr</image>
		<flickrid>2068061555</flickrid>
	</source>
	<owner>
		<flickrid>Unknown</flickrid>
		<name>Unknown</name>
	</owner>
	<size>
		<width>500</width>
		<height>312</height>
		<depth>3</depth>
	</size>
	<segmented>0</segmented>
	<object>
		<name>person</name>
		<pose>Right</pose>
		<truncated>0</truncated>
		<occluded>0</occluded>
		<difficult>0</difficult>
		<bndbox>
			<xmin>119</xmin>
			<ymin>57</ymin>
			<xmax>272</xmax>
			<ymax>268</ymax>
		</bndbox>
		<action>
			<actionname>Running</actionname>
			<ambiguous>0</ambiguous>
		</action>
	</object>
</annotation>
