<annotation>
	<folder>VOC2010</folder>
	<originalfile>462717828_8d309be7a3_o.jpg</originalfile>
	<filename>action0115.jpg</filename>
	<source>
		<database>MyDatabase</database>
		<annotation>MyAnnotation</annotation>
		<image>flickr</image>
		<flickrid>462717828</flickrid>
	</source>
	<owner>
		<flickrid>Unknown</flickrid>
		<name>Unknown</name>
	</owner>
	<size>
		<width>483</width>
		<height>500</height>
		<depth>3</depth>
	</size>
	<segmented>0</segmented>
	<object>
		<name>person</name>
		<pose>Frontal</pose>
		<truncated>0</truncated>
		<occluded>1</occluded>
		<difficult>0</difficult>
		<bndbox>
			<xmin>145</xmin>
			<ymin>35</ymin>
			<xmax>362</xmax>
			<ymax>359</ymax>
		</bndbox>
		<action>
			<actionname>RidingHorse</actionname>
			<ambiguous>0</ambiguous>
		</action>
	</object>
</annotation>
