<annotation>
	<folder>VOC2007</folder>
	<filename>action0384.jpg</filename>
	<source>
		<database>The VOC2007 Database</database>
		<annotation>PASCAL VOC2007</annotation>
		<image>flickr</image>
		<flickrid>293188149</flickrid>
	</source>
	<owner>
		<flickrid>Terenis</flickrid>
		<name>Terenis</name>
	</owner>
	<size>
		<width>500</width>
		<height>334</height>
		<depth>3</depth>
	</size>
	<segmented>0</segmented>
	<object>
		<name>bicycle</name>
		<pose>Right</pose>
		<truncated>0</truncated>
		<difficult>0</difficult>
		<bndbox>
			<xmin>311</xmin>
			<ymin>246</ymin>
			<xmax>432</xmax>
			<ymax>331</ymax>
		</bndbox>
	</object>
	<object>
		<name>bicycle</name>
		<pose>Right</pose>
		<truncated>0</truncated>
		<difficult>0</difficult>
		<bndbox>
			<xmin>66</xmin>
			<ymin>236</ymin>
			<xmax>159</xmax>
			<ymax>304</ymax>
		</bndbox>
	</object>
	<object>
		<name>person</name>
		<pose>Unspecified</pose>
		<truncated>0</truncated>
		<difficult>0</difficult>
		<bndbox>
			<xmin>329</xmin>
			<ymin>200</ymin>
			<xmax>411</xmax>
			<ymax>308</ymax>
		</bndbox>
		<action>
			<actionname>RidingBike</actionname>
			<ambiguous>0</ambiguous>
		</action>
	</object>
	<object>
		<name>person</name>
		<pose>Unspecified</pose>
		<truncated>0</truncated>
		<difficult>0</difficult>
		<bndbox>
			<xmin>74</xmin>
			<ymin>198</ymin>
			<xmax>136</xmax>
			<ymax>297</ymax>
		</bndbox>
		<action>
			<actionname>RidingBike</actionname>
			<ambiguous>0</ambiguous>
		</action>
	</object>
	<originalfile>009534.jpg</originalfile>
</annotation>
