<annotation>
	<folder>VOC2007</folder>
	<filename>action0308.jpg</filename>
	<source>
		<database>The VOC2007 Database</database>
		<annotation>PASCAL VOC2007</annotation>
		<image>flickr</image>
		<flickrid>299026810</flickrid>
	</source>
	<owner>
		<flickrid>Steve HMCC</flickrid>
		<name>Steve Parker</name>
	</owner>
	<size>
		<width>500</width>
		<height>375</height>
		<depth>3</depth>
	</size>
	<segmented>0</segmented>
	<object>
		<name>motorbike</name>
		<pose>Unspecified</pose>
		<truncated>0</truncated>
		<difficult>0</difficult>
		<bndbox>
			<xmin>219</xmin>
			<ymin>113</ymin>
			<xmax>441</xmax>
			<ymax>268</ymax>
		</bndbox>
	</object>
	<object>
		<name>person</name>
		<pose>Unspecified</pose>
		<truncated>0</truncated>
		<difficult>0</difficult>
		<bndbox>
			<xmin>303</xmin>
			<ymin>92</ymin>
			<xmax>415</xmax>
			<ymax>253</ymax>
		</bndbox>
		<action>
			<actionname>RidingBike</actionname>
			<ambiguous>0</ambiguous>
		</action>
	</object>
	<originalfile>005133.jpg</originalfile>
</annotation>
