<annotation>
	<folder>VOC2010</folder>
	<originalfile>3946403595_cc1592bf99_o.jpg</originalfile>
	<filename>action0948.jpg</filename>
	<source>
		<database>MyDatabase</database>
		<annotation>MyAnnotation</annotation>
		<image>flickr</image>
		<flickrid>3946403595</flickrid>
	</source>
	<owner>
		<flickrid>Unknown</flickrid>
		<name>Unknown</name>
	</owner>
	<size>
		<width>375</width>
		<height>500</height>
		<depth>3</depth>
	</size>
	<segmented>0</segmented>
	<object>
		<name>person</name>
		<pose>Left</pose>
		<truncated>0</truncated>
		<occluded>0</occluded>
		<difficult>0</difficult>
		<bndbox>
			<xmin>114</xmin>
			<ymin>21</ymin>
			<xmax>316</xmax>
			<ymax>478</ymax>
		</bndbox>
		<action>
			<actionname>Walking</actionname>
			<ambiguous>0</ambiguous>
		</action>
	</object>
</annotation>
